dumbpw/__init__.py
dumbpw/candidate.py
dumbpw/charspace.py
dumbpw/cli.py
dumbpw/constants.py
dumbpw/engine.py
dumbpw/exceptions.py
dumbpw/settings.py
dumbpw-1.0.0.dist-info/LICENSE
dumbpw-1.0.0.dist-info/METADATA
dumbpw-1.0.0.dist-info/WHEEL
dumbpw-1.0.0.dist-info/entry_points.txt
dumbpw-1.0.0.dist-info/RECORD
