Metadata-Version: 2.3
Name: dumbpw
Version: 1.0.0
Summary: A bad password generator for bad websites with bad password policies
License: Apache 2.0
Author: Ryan Delaney
Author-email: ryan.patrick.delaney+git@protonmail.com
Requires-Python: >=3.10,<4.0
Classifier: Development Status :: 5 - Production/Stable
Classifier: Environment :: Console
Classifier: License :: OSI Approved :: Apache Software License
Classifier: License :: Other/Proprietary License
Classifier: Programming Language :: Python :: 3
Classifier: Programming Language :: Python :: 3.10
Classifier: Programming Language :: Python :: 3.11
Classifier: Programming Language :: Python :: 3.12
Classifier: Programming Language :: Python :: 3.13
Classifier: Programming Language :: Python :: 3 :: Only
Classifier: Topic :: Security
Requires-Dist: click (>=8.0.3)
Requires-Dist: deal (>=4.19.1)
Project-URL: Homepage, https://pypi.org/project/dumbpw
Project-URL: Repository, https://github.com/rpdelaney/dumbpw
